fmiprecice/__init__.py
fmiprecice/runner.py
fmiprecice-0.2.1.dist-info/LICENSE
fmiprecice-0.2.1.dist-info/METADATA
fmiprecice-0.2.1.dist-info/WHEEL
fmiprecice-0.2.1.dist-info/entry_points.txt
fmiprecice-0.2.1.dist-info/top_level.txt
fmiprecice-0.2.1.dist-info/RECORD
