Metadata-Version: 2.1
Name: fmiprecice
Version: 0.2.1
Summary: A tool to co-simulate FMU models with the coupling library preCICE.
Author-email: The preCICE Developers <info@precice.org>
Maintainer-email: Benjamin Uekermann <benjamin.uekermann@ipvs.uni-stuttgart.de>
License: LGPL-3.0
Project-URL: Homepage, https://precice.org
Project-URL: Documentation, https://precice.org/tooling-fmi-runner.html
Project-URL: Repository, https://github.com/precice/fmi-runner
Project-URL: Bug Tracker, https://github.com/precice/fmi-runner/issues
Keywords: preCICE,FMI,ODE,controller,PDE,coupling
Classifier: Development Status :: 4 - Beta
Classifier: License :: OSI Approved :: GNU Lesser General Public License v3 (LGPLv3)
Classifier: Programming Language :: Python :: 3 :: Only
Classifier: Programming Language :: Python :: 3.8
Classifier: Topic :: Scientific/Engineering
Requires-Python: >=3.8
License-File: LICENSE
Requires-Dist: fmpy
Requires-Dist: numpy
Requires-Dist: pyprecice >=3.0
